pystics/__init__.py
pystics/_version.py
pystics/exceptions.py
pystics/params.py
pystics/simulation.py
pystics/modules/canopy_microclimate.py
pystics/modules/day_zero.py
pystics/modules/development.py
pystics/modules/foliage_water_interception.py
pystics/modules/forage_cutting.py
pystics/modules/initialization.py
pystics/modules/irrigation.py
pystics/modules/lethal_frost.py
pystics/modules/senescence.py
pystics/modules/soil_temperature.py
pystics/modules/soil_tillage.py
pystics/modules/water_potential.py
pystics/modules/weather_variables.py
pystics/modules/et0/fao.py
pystics/modules/growth/biomass.py
pystics/modules/growth/biomass_partitioning.py
pystics/modules/growth/harvest_criteria.py
pystics/modules/growth/leaf_growth.py
pystics/modules/growth/plant_height.py
pystics/modules/growth/radiative_stress.py
pystics/modules/growth/roots.py
pystics/modules/growth/thermal_stress_indices.py
pystics/modules/growth/yield_formation_determinate.py
pystics/modules/growth/yield_formation_forage.py
pystics/modules/water/potential_evapotranspiration.py
pystics/modules/water/soil_evaporation.py
pystics/modules/water/transpiration.py
pystics/modules/water/water_balance.py
pystics/modules/water/water_stress.py
pystics/parametrization_files/example/Auzeville.2012
pystics/parametrization_files/example/Auzeville.2013
pystics/parametrization_files/example/Auzeville.2014
pystics/parametrization_files/example/AuzevilleJ_sta.xml
pystics/parametrization_files/example/BareSoil.obs
pystics/parametrization_files/example/Ble_tec.xml
pystics/parametrization_files/example/Colza_tec.xml
pystics/parametrization_files/example/DurumWheat.obs
pystics/parametrization_files/example/Fraise_tec.xml
pystics/parametrization_files/example/Mais_tec.xml
pystics/parametrization_files/example/Miscanthus.2006
pystics/parametrization_files/example/Miscanthus.2007
pystics/parametrization_files/example/Miscanthus.2008
pystics/parametrization_files/example/Miscanthus.2009
pystics-1.2.5.dist-info/METADATA
pystics-1.2.5.dist-info/WHEEL
pystics-1.2.5.dist-info/licenses/LICENSE
pystics-1.2.5.dist-info/RECORD
